pyotb/__init__.py
pyotb/apps.py
pyotb/core.py
pyotb/functions.py
pyotb/helpers.py
pyotb-2.2.1.dist-info/licenses/AUTHORS.md
pyotb-2.2.1.dist-info/licenses/LICENSE
pyotb-2.2.1.dist-info/METADATA
pyotb-2.2.1.dist-info/WHEEL
pyotb-2.2.1.dist-info/top_level.txt
pyotb-2.2.1.dist-info/RECORD
