Metadata-Version: 2.4
Name: pyotb
Version: 2.2.1
Summary: Library to enable easy use of the Orfeo ToolBox (OTB) in Python
Author: Nicolas Narçon, Vincent Delbar
Author-email: Rémi Cresson <remi.cresson@inrae.fr>
License-Expression: Apache-2.0
Project-URL: documentation, https://pyotb.readthedocs.io
Project-URL: homepage, https://github.com/orfeotoolbox/pyotb
Project-URL: repository, https://forgemia.inra.fr/orfeo-toolbox/pyotb
Keywords: gis,remote sensing,otb,orfeotoolbox,orfeo toolbox
Classifier: Programming Language :: Python :: 3
Classifier: Programming Language :: Python :: 3.7
Classifier: Programming Language :: Python :: 3.8
Classifier: Programming Language :: Python :: 3.9
Classifier: Programming Language :: Python :: 3.10
Classifier: Programming Language :: Python :: 3.11
Classifier: Programming Language :: Python :: 3.12
Classifier: Topic :: Scientific/Engineering :: GIS
Classifier: Topic :: Scientific/Engineering :: Image Processing
Classifier: Operating System :: OS Independent
Requires-Python: >=3.7
License-File: LICENSE
License-File: AUTHORS.md
Requires-Dist: numpy<2,>=1.16
Provides-Extra: dev
Requires-Dist: pytest; extra == "dev"
Requires-Dist: pytest-cov; extra == "dev"
Requires-Dist: pylint; extra == "dev"
Requires-Dist: codespell; extra == "dev"
Requires-Dist: pydocstyle; extra == "dev"
Requires-Dist: tomli; extra == "dev"
Requires-Dist: requests; extra == "dev"
Dynamic: license-file
